genderizerQc/__init__.py
genderizerQc/genderizer.py
genderizerQc/data/filles1980-2020.csv
genderizerQc/data/gars1980-2020.csv
genderizerQc-0.1.2.dist-info/LICENSE
genderizerQc-0.1.2.dist-info/METADATA
genderizerQc-0.1.2.dist-info/WHEEL
genderizerQc-0.1.2.dist-info/top_level.txt
genderizerQc-0.1.2.dist-info/RECORD
